cassandra/ioutils.pyx
cassandra/deserializers.pyx
cassandra/parsing.pyx
cassandra/cython_utils.pyx
cassandra/numpy_parser.so
cassandra/connection.so
cassandra/row_parser.pyx
cassandra/type_codes.py
cassandra/parsing.so
cassandra/buffer.pxd
cassandra/encoder.py
cassandra/concurrent.so
cassandra/obj_parser.pyx
cassandra/util.py
cassandra/type_codes.pxd
cassandra/bytesio.pxd
cassandra/pool.py
cassandra/ioutils.so
cassandra/connection.py
cassandra/cluster.so
cassandra/bytesio.so
cassandra/cython_deps.py
cassandra/cmurmur3.c
cassandra/metadata.so
cassandra/cython_marshal.pyx
cassandra/cython_utils.pxd
cassandra/murmur3.py
cassandra/numpyFlags.h
cassandra/__init__.py
cassandra/cmurmur3.so
cassandra/parsing.pxd
cassandra/auth.py
cassandra/policies.py
cassandra/marshal.py
cassandra/row_parser.so
cassandra/cython_marshal.so
cassandra/obj_parser.so
cassandra/protocol.py
cassandra/protocol.so
cassandra/metadata.py
cassandra/cython_utils.so
cassandra/numpy_parser.pyx
cassandra/util.so
cassandra/pool.so
cassandra/query.so
cassandra/cqltypes.so
cassandra/concurrent.py
cassandra/deserializers.pxd
cassandra/cluster.py
cassandra/deserializers.so
cassandra/query.py
cassandra/cqltypes.py
cassandra/timestamps.py
cassandra/bytesio.pyx
cassandra/tuple.pxd
cassandra/metrics.py
cassandra/cqlengine/operators.py
cassandra/cqlengine/statements.py
cassandra/cqlengine/usertype.py
cassandra/cqlengine/models.py
cassandra/cqlengine/connection.py
cassandra/cqlengine/__init__.py
cassandra/cqlengine/functions.py
cassandra/cqlengine/query.py
cassandra/cqlengine/named.py
cassandra/cqlengine/columns.py
cassandra/cqlengine/management.py
cassandra/.libs/libev-a9cd1492.so.4.0.0
cassandra/io/libevwrapper.c
cassandra/io/asyncorereactor.py
cassandra/io/twistedreactor.py
cassandra/io/__init__.py
cassandra/io/libevwrapper.so
cassandra/io/eventletreactor.py
cassandra/io/libevreactor.py
cassandra/io/geventreactor.py
arun_cassandra_driver-3.12.dist-info/METADATA
arun_cassandra_driver-3.12.dist-info/RECORD
arun_cassandra_driver-3.12.dist-info/WHEEL
arun_cassandra_driver-3.12.dist-info/top_level.txt
arun_cassandra_driver-3.12.dist-info/DESCRIPTION.rst
arun_cassandra_driver-3.12.dist-info/metadata.json
